[{"business_model": "\n- Sản xuất kinh doanh dược phẩm, vật tư y tế, kinh doanh mỹ phẩm.\n- Sản xuất, gia công các loại thực phẩm và thực phẩm chức năng.\n- Mua bán dược phẩm, vật tư y tế, hóa chất (không thuộc danh mục cấm) nguyên liệu phục vụ cho sản xuất dược phẩm, mỹ phẩm, thực phẩm và thực phẩm chức năng.\n- Kinh doanh bất động sản, quyền sử dụng đất thuộc chủ sở hữu.\n- Bán buôn vật liệu, thiết bị lắp đặt khác trong xây dựng.", "symbol": "BCP", "founded_date": "", "charter_capital": 60, "number_of_employees": 128, "listing_date": "14/09/2015", "par_value": 10000, "exchange": "UPCoM", "listing_price": 13400, "listed_volume": 6, "ceo_name": "Mr. An Mạnh Hùng", "ceo_position": "Tổng Giám đốc", "inspector_name": "Phan Tấn Anh Việt\t", "inspector_position": "Giám đốc sản xuất", "establishment_license": "", "business_code": "4603000202", "tax_id": "3700683163", "auditor": "A&C", "company_type": "Công ty cổ phần", "address": "Đường NA6 - KCN Mỹ Phước 2 - P. Bến Cát - Tp. Hồ Chí Minh", "phone": "(84-274) 355 3326", "fax": "(84.274) 355 3327", "email": "nliepharma@enlie.vn", "website": "http://enlie.vn", "branches": "", "history": "\n- Tiền thân là Công ty Dược Phẩm Tỉnh Sông Bé \n- Năm 1992, UBND tỉnh Sông Bé ký quyết định giải thể các công ty Dược cấp III huyện, thị và nhập thành Công ty Dược phẩm tỉnh Sông Bé hình thành 1 công ty dược duy nhất tại tỉnh\n- Ngày 08/12/1992, chính thức thành lập công ty Dược với tên gọi là Công ty Dược Vật Tư Y Tế Bình Dương\n- Ngày 10/11/2004, UBND tỉnh Bình Dương ra quyết định sáp nhập CTCP dược và vật tư y tế Bình Dương vào Công ty Đầu tư và phát triển công nghiệp (Becamex IDC) và quyết định thành lập Công ty Dược và Vật tư y tế Bình Dương trực thuộc công ty Đầu tư và phát triển công nghiệp (Becamex IDC)\n- Ngày 29/12/2005, công ty chính thức chuyển thể thành công ty cổ phần với tên gọi là CTCP Dược và vật tư y tế Bình Dương với VĐL 15 tỷ đồng\n- Đầu năm 2007, được đầu tư xây dựng và chính thức đi vào hoạt động sản xuất tháng 08/2009, CTCP Dược Becamex được thành lập trên cơ sở tiếp quản từ CTCP Dược và Vật tư y tế Bình Dương trước đây. Chuyển đổi môi trường hoạt động với đơn vị chủ quản đầu tư trực tiếp là TCT Đầu tư và phát triển Công nghiệp TNHH-MTV Becamex IDC\n- Ngày 25/08/2015, ngày đăng ký giao dịch đầu tiên trên UPCoM với mã chứng khoán là BCP\n- Ngày 14/09/2015, ngày giao dịch đầu tiên của BCP trên UPCoM với giá đóng cửa cuối phiên 13,400 đồng/CP\n- Ngày 24/07/2019 đổi tên thành CTCP Dược Enlie.", "free_float_percentage": 60000000000, "free_float": 10000, "outstanding_shares": 6000000, "as_of_date": "2025-12-31T00:00:00"}]